assets/COPYRIGHT
assets/LICENSE
assets/sprites/ball_blue.png
assets/sprites/ball_green.png
assets/sprites/ball_grey.png
assets/sprites/ball_purple.png
assets/sprites/ball_red.png
assets/sprites/ball_yellow.png
assets/sprites/box_blue.png
assets/sprites/box_green.png
assets/sprites/box_grey.png
assets/sprites/box_purple.png
assets/sprites/box_red.png
assets/sprites/box_yellow.png
assets/sprites/door_closed_blue.png
assets/sprites/door_closed_green.png
assets/sprites/door_closed_grey.png
assets/sprites/door_closed_purple.png
assets/sprites/door_closed_red.png
assets/sprites/door_closed_yellow.png
assets/sprites/door_locked_blue.png
assets/sprites/door_locked_green.png
assets/sprites/door_locked_grey.png
assets/sprites/door_locked_purple.png
assets/sprites/door_locked_red.png
assets/sprites/door_locked_yellow.png
assets/sprites/door_open_blue.png
assets/sprites/door_open_green.png
assets/sprites/door_open_grey.png
assets/sprites/door_open_purple.png
assets/sprites/door_open_red.png
assets/sprites/door_open_yellow.png
assets/sprites/floor.png
assets/sprites/goal.png
assets/sprites/key_blue.png
assets/sprites/key_green.png
assets/sprites/key_grey.png
assets/sprites/key_purple.png
assets/sprites/key_red.png
assets/sprites/key_yellow.png
assets/sprites/lava.png
assets/sprites/player_east.png
assets/sprites/player_north.png
assets/sprites/player_south.png
assets/sprites/player_west.png
assets/sprites/wall.png
navix/__init__.py
navix/_version.py
navix/actions.py
navix/components.py
navix/config.py
navix/entities.py
navix/events.py
navix/experiment.py
navix/grid.py
navix/observations.py
navix/rewards.py
navix/spaces.py
navix/states.py
navix/tasks.py
navix/terminations.py
navix/transitions.py
navix/agents/__init__.py
navix/agents/agent.py
navix/agents/models.py
navix/agents/ppo.py
navix/environments/__init__.py
navix/environments/crossings.py
navix/environments/dist_shift.py
navix/environments/door_key.py
navix/environments/dynamic_obstacles.py
navix/environments/empty.py
navix-0.7.4.dist-info/licenses/AUTHORS
navix-0.7.4.dist-info/licenses/LICENSE
navix-0.7.4.dist-info/licenses/NOTICE
navix-0.7.4.dist-info/METADATA
navix-0.7.4.dist-info/WHEEL
navix-0.7.4.dist-info/top_level.txt
navix-0.7.4.dist-info/RECORD
